brec/dataset.py
brec/evaluator.py
brec_iclr2024-1.0.0.dist-info/LICENSE
brec_iclr2024-1.0.0.dist-info/METADATA
brec_iclr2024-1.0.0.dist-info/WHEEL
brec_iclr2024-1.0.0.dist-info/top_level.txt
brec_iclr2024-1.0.0.dist-info/RECORD
